{"name": "Macdonald's Collection 2014", "id": "2014xy", "cardCount": 12, "cards": [12, {"name": "Weedle", "id": "2014xy-1", "rarity": "None", "category": "Pokemon", "types": ["Grass"], "hp": 40}, {"name": "Chespin", "id": "2014xy-2", "rarity": "None", "category": "Pokemon", "types": ["Grass"], "hp": 60}, {"name": "Fennekin", "id": "2014xy-3", "rarity": "None", "category": "Pokemon", "types": ["Fire"], "hp": 60}, {"name": "Froakie", "id": "2014xy-4", "rarity": "None", "category": "Pokemon", "types": ["Water"], "hp": 60}, {"name": "Pikachu", "id": "2014xy-5", "rarity": "None", "category": "Pokemon", "types": ["Lightning"], "hp": 60}, {"name": "Inkay", "id": "2014xy-6", "rarity": "None", "category": "Pokemon", "types": ["Darkness"], "hp": 60}, {"name": "Honedge", "id": "2014xy-7", "rarity": "None", "category": "Pokemon", "types": ["Metal"], "hp": 60}, {"name": "Snubbull", "id": "2014xy-8", "rarity": "None", "category": "Pokemon", "types": ["Fairy"], "hp": 70}, {"name": "Swirlix", "id": "2014xy-9", "rarity": "None", "category": "Pokemon", "types": ["Fairy"], "hp": 60}, {"name": "Bunnelby", "id": "2014xy-10", "rarity": "None", "category": "Pokemon", "types": ["Colorless"], "hp": 60}, {"name": "Fletchling", "id": "2014xy-11", "rarity": "None", "category": "Pokemon", "types": ["Colorless"], "hp": 50}, {"name": "Furfrou", "id": "2014xy-12", "rarity": "None", "category": "Pokemon", "types": ["Colorless"], "hp": 90}]}
