{"name": "XY trainer Kit (Pikachu Libre)", "id": "tk-xy-p", "logo": "https://assets.tcgdex.net/univ/tk/tk-xy-p/symbol.png", "cardCount": 30, "cards": [30, {"name": "Glameow", "id": "tk-xy-p-1", "rarity": "Common", "category": "Pokemon", "types": ["Colorless"], "hp": 60, "weaknesses": [{"type": "Fighting", "value": "\u00d72"}], "retreat": 1}, {"name": "Lightning Energy", "id": "tk-xy-p-2", "rarity": "Common", "category": "Energy"}, {"name": "Lightning Energy", "id": "tk-xy-p-3", "rarity": "Common", "category": "Energy"}, {"name": "Electivire", "id": "tk-xy-p-4", "rarity": "Uncommon", "category": "Pokemon", "types": ["Lightning"], "hp": 110, "evolveFrom": "Electabuzz", "weaknesses": [{"type": "Fighting", "value": "\u00d72"}], "retreat": 3}, {"name": "Lightning Energy", "id": "tk-xy-p-5", "rarity": "Common", "category": "Energy"}, {"name": "Lightning Energy", "id": "tk-xy-p-6", "rarity": "Common", "category": "Energy"}, {"name": "Taillow", "id": "tk-xy-p-7", "rarity": "None", "category": "Pokemon", "types": ["Colorless"], "hp": 50, "attacks": [{"name": "Double Peck", "effect": "Flip 2 coins. This attack does 10 damage times the number of heads.", "damage": "10\u00d7"}], "weaknesses": [{"type": "Lightning", "value": "\u00d72"}], "retreat": 1}, {"name": "Lightning Energy", "id": "tk-xy-p-8", "rarity": "Common", "category": "Energy"}, {"name": "Lightning Energy", "id": "tk-xy-p-9", "rarity": "Common", "category": "Energy"}, {"name": "Lightning Energy", "id": "tk-xy-p-10", "rarity": "Common", "category": "Energy"}, {"name": "Electrike", "id": "tk-xy-p-11", "rarity": "None", "category": "Pokemon", "types": ["Lightning"], "hp": 60, "attacks": [{"name": "Bite", "damage": 10}], "weaknesses": [{"type": "Fighting", "value": "\u00d72"}], "retreat": 1}, {"name": "Blitzle", "id": "tk-xy-p-12", "rarity": "Common", "category": "Pokemon", "types": ["Lightning"], "hp": 60, "weaknesses": [{"type": "Fighting", "value": "\u00d72"}], "retreat": 1}, {"name": "Manectric", "id": "tk-xy-p-13", "rarity": "None", "category": "Pokemon", "types": ["Lightning"], "hp": 90, "evolveFrom": "Electrike", "attacks": [{"name": "Random Spark", "effect": "This attack does 30 damage to 1 of your opponent\u2019s Pok\u00e9mon. (Don\u2019t apply Weakness and Resistance for Benched Pok\u00e9mon.)"}, {"name": "Bite", "damage": 40}], "weaknesses": [{"type": "Fighting", "value": "\u00d72"}], "retreat": 1}, {"name": "Pikachu Libre", "id": "tk-xy-p-14", "rarity": "None", "category": "Pokemon", "types": ["Lightning"], "hp": 80, "attacks": [{"name": "Quick Attack", "effect": "Flip a coin. If heads, this attack does 30 more damage.", "damage": "10+"}, {"name": "Flying Elekick", "damage": 50}], "weaknesses": [{"type": "Fighting", "value": "\u00d72"}], "retreat": 1}, {"name": "Electabuzz", "id": "tk-xy-p-15", "rarity": "Common", "category": "Pokemon", "types": ["Lightning"], "hp": 70, "weaknesses": [{"type": "Fighting", "value": "\u00d72"}], "retreat": 2}, {"name": "Fletchling", "id": "tk-xy-p-16", "rarity": "None", "category": "Pokemon", "types": ["Colorless"], "hp": 40, "attacks": [{"name": "Acrobatics", "effect": "Flip 2 coins. This attack does 10 more damage for each heads.", "damage": "10+"}], "weaknesses": [{"type": "Lightning", "value": "\u00d72"}], "retreat": 1}, {"name": "Lightning Energy", "id": "tk-xy-p-17", "rarity": "Common", "category": "Energy"}, {"name": "Lightning Energy", "id": "tk-xy-p-18", "rarity": "Common", "category": "Energy"}, {"name": "Purugly", "id": "tk-xy-p-19", "rarity": "Uncommon", "category": "Pokemon", "types": ["Colorless"], "hp": 100, "evolveFrom": "Glameow", "weaknesses": [{"type": "Fighting", "value": "\u00d72"}], "retreat": 2}, {"name": "Tierno", "id": "tk-xy-p-20", "rarity": "Uncommon", "category": "Trainer", "effect": "Draw 3 cards.", "trainerType": "Supporter"}, {"name": "Potion", "id": "tk-xy-p-21", "rarity": "Uncommon", "category": "Trainer", "effect": "Heal 30 damage from 1 of your Pok\u00e9mon.", "trainerType": "Item"}, {"name": "Manectric", "id": "tk-xy-p-22", "rarity": "None", "category": "Pokemon", "types": ["Lightning"], "hp": 90, "evolveFrom": "Electrike", "attacks": [{"name": "Random Spark", "effect": "This attack does 30 damage to 1 of your opponent\u2019s Pok\u00e9mon. (Don\u2019t apply Weakness and Resistance for Benched Pok\u00e9mon.)"}, {"name": "Bite", "damage": 40}], "weaknesses": [{"type": "Fighting", "value": "\u00d72"}], "retreat": 1}, {"name": "Electabuzz", "id": "tk-xy-p-23", "rarity": "Common", "category": "Pokemon", "types": ["Lightning"], "hp": 70, "weaknesses": [{"type": "Fighting", "value": "\u00d72"}], "retreat": 2}, {"name": "Purugly", "id": "tk-xy-p-24", "rarity": "Uncommon", "category": "Pokemon", "types": ["Colorless"], "hp": 100, "evolveFrom": "Glameow", "weaknesses": [{"type": "Fighting", "value": "\u00d72"}], "retreat": 2}, {"name": "Electivire", "id": "tk-xy-p-25", "rarity": "Uncommon", "category": "Pokemon", "types": ["Lightning"], "hp": 110, "evolveFrom": "Electabuzz", "weaknesses": [{"type": "Fighting", "value": "\u00d72"}], "retreat": 3}, {"name": "Blitzle", "id": "tk-xy-p-26", "rarity": "Common", "category": "Pokemon", "types": ["Lightning"], "hp": 60, "weaknesses": [{"type": "Fighting", "value": "\u00d72"}], "retreat": 1}, {"name": "Glameow", "id": "tk-xy-p-27", "rarity": "Common", "category": "Pokemon", "types": ["Colorless"], "hp": 60, "weaknesses": [{"type": "Fighting", "value": "\u00d72"}], "retreat": 1}, {"name": "Electrike", "id": "tk-xy-p-28", "rarity": "None", "category": "Pokemon", "types": ["Lightning"], "hp": 60, "attacks": [{"name": "Bite", "damage": 10}], "weaknesses": [{"type": "Fighting", "value": "\u00d72"}], "retreat": 1}, {"name": "Lightning Energy", "id": "tk-xy-p-29", "rarity": "Common", "category": "Energy"}, {"name": "Pikachu Libre", "id": "tk-xy-p-30", "rarity": "None", "category": "Pokemon", "types": ["Lightning"], "hp": 80, "attacks": [{"name": "Quick Attack", "effect": "Flip a coin. If heads, this attack does 30 more damage.", "damage": "10+"}, {"name": "Flying Elekick", "damage": 50}], "weaknesses": [{"type": "Fighting", "value": "\u00d72"}], "retreat": 1}]}
